{"stats":{"minecraft:broken":{"minecraft:diamond_helmet":1,"minecraft:shield":1,"minecraft:iron_helmet":1},"minecraft:killed":{"minecraft:cave_spider":15,"minecraft:witch":1,"minecraft:spider":17,"minecraft:skeleton":285,"minecraft:chicken":2,"minecraft:pig":20,"minecraft:zombie_villager":3,"minecraft:iron_golem":4,"minecraft:creeper":6,"minecraft:sheep":52,"minecraft:zombie":212,"minecraft:stray":30,"minecraft:cow":23,"minecraft:breeze":2,"minecraft:player":2,"minecraft:enderman":6},"minecraft:picked_up":{"minecraft:iron_chestplate":1,"minecraft:flower_pot":2,"minecraft:anvil":7,"minecraft:oak_stairs":1,"minecraft:potion":1,"minecraft:enchanted_book":2,"minecraft:stone_brick_stairs":1,"spell_engine:scroll":5,"minecraft:string":52,"minecraft:raw_copper":19,"minecraft:smooth_stone_slab":31,"minecraft:iron_leggings":3,"minecraft:zombie_head":1,"minecraft:smooth_stone":11,"minecraft:gold_nugget":23,"minecraft:cobbled_deepslate":654,"bosses_of_mass_destruction:soul_star":6,"minecraft:spruce_planks":3,"minecraft:trial_key":7,"minecraft:white_tulip":1,"minecraft:cobblestone_slab":1,"minecraft:azalea":6,"minecraft:iron_pickaxe":4,"paladins:iron_great_hammer":1,"minecraft:furnace":4,"minecraft:iron_boots":2,"minecraft:tipped_arrow":27,"minecraft:stick":155,"paladins:diamond_claymore":2,"minecraft:big_dripleaf":2,"minecraft:torch":91,"minecraft:porkchop":43,"minecraft:waxed_copper_grate":3,"minecraft:pointed_dripstone":2,"minecraft:diorite":1,"minecraft:stone_sword":1,"minecraft:honey_bottle":2,"minecraft:rotten_flesh":140,"minecraft:tropical_fish":2,"supplementaries:antique_ink":6,"minecraft:red_tulip":6,"minecraft:cyan_terracotta":5,"supplementaries:ash":57,"minecraft:obsidian":30,"minecraft:cobblestone":468,"minecraft:feather":3,"minecraft:cooked_beef":74,"minecraft:water_bucket":2,"minecraft:andesite":129,"minecraft:brown_wool":1,"minecraft:potato":1,"minecraft:flint":13,"minecraft:tuff":25,"minecraft:lantern":3,"minecraft:lapis_lazuli":235,"minecraft:dirt":33,"minecraft:brown_candle":2,"minecraft:name_tag":2,"minecraft:bone":277,"minecraft:bow":5,"minecraft:orange_tulip":3,"minecraft:wheat_seeds":2,"minecraft:green_candle":3,"minecraft:raw_gold":16,"minecraft:bell":7,"archers:netherite_longbow":1,"minecraft:grindstone":1,"minecraft:glowstone_dust":2,"minecraft:moss_block":21,"minecraft:scrape_pottery_sherd":1,"minecraft:stone_hoe":1,"minecraft:oak_planks":258,"minecraft:cooked_porkchop":94,"minecraft:grass_block":2,"minecraft:mossy_cobblestone":47,"minecraft:polished_andesite":29,"minecraft:white_candle":4,"minecraft:diamond":349,"minecraft:spruce_boat":1,"waystones:waystone":1,"minecraft:crossbow":1,"minecraft:breeze_rod":3,"minecraft:golden_apple":5,"minecraft:emerald":74,"minecraft:bread":73,"minecraft:oak_sapling":1,"minecraft:bricks":2,"minecraft:diamond_pickaxe":1,"minecraft:coarse_dirt":68,"minecraft:crafting_table":26,"minecraft:ominous_bottle":1,"minecraft:chicken":2,"minecraft:ladder":1,"minecraft:clay_ball":200,"runes:crafting_altar":4,"minecraft:brick":97,"minecraft:shield":1,"minecraft:cornflower":10,"minecraft:moss_carpet":18,"minecraft:iron_shovel":2,"farmersdelight:beef_patty":18,"minecraft:candle":6,"minecraft:beef":25,"minecraft:guster_pottery_sherd":1,"minecraft:iron_nugget":8,"minecraft:spruce_slab":29,"minecraft:light_gray_wool":4,"minecraft:poppy":10,"minecraft:lectern":6,"minecraft:sugar_cane":39,"minecraft:birch_sapling":1,"paladins:diamond_great_hammer":1,"minecraft:waxed_oxidized_copper":1,"minecraft:egg":4,"minecraft:raw_iron":77,"minecraft:flow_pottery_sherd":4,"minecraft:music_disc_creator_music_box":1,"minecraft:blue_carpet":3,"minecraft:arrow":278,"archers:archer_armor_feet":1,"minecraft:hay_block":26,"spell_engine:spell_binding":6,"minecraft:gold_ingot":4,"paladins:prior_robe_head":1,"minecraft:tuff_bricks":4,"minecraft:mutton":96,"minecraft:skeleton_skull":3,"minecraft:white_wool":76,"minecraft:oxeye_daisy":1,"minecraft:glow_ink_sac":5,"minecraft:leather":55,"minecraft:red_mushroom":2,"minecraft:oak_log":43,"minecraft:waxed_copper_block":2,"minecraft:gunpowder":9,"minecraft:cobblestone_stairs":1,"minecraft:paper":12,"minecraft:cooked_mutton":102,"minecraft:apple":17,"minecraft:iron_ingot":52,"minecraft:stone_pickaxe":2,"minecraft:glass_bottle":4,"minecraft:iron_sword":14,"minecraft:book":135,"minecraft:polished_andesite_stairs":15,"minecraft:emerald_block":1,"minecraft:black_candle":1,"minecraft:pumpkin":7,"minecraft:gravel":17,"minecraft:amethyst_shard":4,"minecraft:blast_furnace":17,"minecraft:white_bed":6,"minecraft:spruce_log":1,"minecraft:polished_tuff":1,"minecraft:spider_eye":13,"paladins:paladin_armor_feet":1,"minecraft:stone_axe":2,"minecraft:iron_helmet":2,"paladins:holy_wand":1,"archers:rapid_crossbow":1,"minecraft:mossy_cobblestone_stairs":4,"minecraft:gray_wool":1,"minecraft:damaged_anvil":3,"minecraft:black_wool":2,"minecraft:stripped_dark_oak_log":8,"minecraft:coal":192,"minecraft:ender_pearl":4},"minecraft:crafted":{"minecraft:oak_planks":156,"usefulbackpacks:backpack_small":2,"minecraft:bookshelf":17,"minecraft:cooked_mutton":27,"minecraft:diamond_helmet":2,"minecraft:diamond_leggings":2,"minecraft:iron_boots":1,"minecraft:stone_hoe":1,"paladins:diamond_claymore":3,"minecraft:cooked_porkchop":35,"minecraft:diamond_axe":1,"minecraft:crafting_table":8,"minecraft:spruce_planks":156,"minecraft:wooden_pickaxe":1,"minecraft:iron_helmet":1,"waystones:warp_stone":1,"minecraft:iron_chestplate":1,"minecraft:diamond_pickaxe":4,"minecraft:shield":2,"minecraft:stick":88,"usefulbackpacks:backpack_large":4,"minecraft:iron_ingot":54,"minecraft:iron_pickaxe":1,"minecraft:stone_sword":1,"minecraft:diamond_hoe":1,"minecraft:furnace":3,"minecraft:polished_andesite_slab":6,"minecraft:flint_and_steel":1,"minecraft:iron_axe":1,"paladins:diamond_kite_shield":1,"minecraft:spruce_slab":96,"minecraft:stone_pickaxe":1,"minecraft:diamond_boots":2,"usefulbackpacks:backpack_medium":2,"minecraft:spruce_boat":1,"minecraft:wheat":126,"minecraft:cooked_beef":14,"minecraft:red_dye":7,"minecraft:enchanting_table":1,"paladins:diamond_great_hammer":1,"minecraft:iron_sword":2,"archers:diamond_spear":1,"minecraft:stone_axe":2,"minecraft:bread":42,"minecraft:air":0,"minecraft:blue_dye":10,"minecraft:wooden_axe":1,"minecraft:iron_leggings":1,"minecraft:white_bed":3,"minecraft:torch":68,"minecraft:diamond_chestplate":2},"minecraft:mined":{"minecraft:blue_carpet":3,"minecraft:spruce_planks":3,"minecraft:white_bed":3,"minecraft:cobblestone_stairs":1,"minecraft:sculk_vein":56,"minecraft:grass_block":8,"minecraft:oxeye_daisy":1,"minecraft:tuff_bricks":4,"minecraft:smooth_stone":10,"minecraft:sculk_catalyst":5,"minecraft:mossy_cobblestone_stairs":4,"minecraft:iron_ore":59,"minecraft:cobbled_deepslate":26,"minecraft:fire":27,"minecraft:polished_tuff":1,"minecraft:pumpkin":7,"minecraft:deepslate_lapis_ore":19,"minecraft:anvil":7,"minecraft:sculk_shrieker":1,"minecraft:red_tulip":6,"minecraft:flowering_azalea_leaves":2,"minecraft:oak_stairs":1,"minecraft:azalea_leaves":9,"minecraft:azalea":1,"minecraft:spruce_slab":24,"minecraft:cyan_terracotta":5,"minecraft:soul_fire":1,"minecraft:amethyst_cluster":1,"minecraft:clay":25,"minecraft:torch":33,"minecraft:blast_furnace":14,"minecraft:poppy":6,"minecraft:polished_andesite_stairs":15,"minecraft:chest":1,"minecraft:white_stained_glass_pane":1,"minecraft:white_candle":1,"minecraft:cobblestone":93,"minecraft:grindstone":1,"minecraft:sugar_cane":7,"minecraft:oak_planks":8,"minecraft:damaged_anvil":1,"minecraft:bricks":2,"minecraft:wall_torch":28,"minecraft:skeleton_skull":3,"minecraft:blue_ice":2,"minecraft:waxed_copper_block":2,"minecraft:orange_tulip":3,"minecraft:smooth_stone_slab":30,"minecraft:stone_brick_stairs":2,"minecraft:oak_log":42,"minecraft:waxed_oxidized_copper":1,"minecraft:dirt":8,"minecraft:deepslate":629,"minecraft:light_blue_stained_glass_pane":3,"minecraft:tuff":31,"minecraft:mossy_cobblestone":52,"minecraft:deepslate_diamond_ore":170,"minecraft:candle":1,"minecraft:ladder":1,"minecraft:decorated_pot":28,"minecraft:moss_block":2,"minecraft:large_fern":1,"minecraft:hay_block":26,"minecraft:furnace":5,"minecraft:waxed_copper_grate":3,"runes:crafting_altar":4,"minecraft:andesite":130,"minecraft:stripped_spruce_log":1,"minecraft:big_dripleaf_stem":1,"minecraft:chiseled_tuff":1,"minecraft:bell":3,"minecraft:bookshelf":45,"minecraft:deepslate_iron_ore":7,"minecraft:cobblestone_slab":2,"minecraft:lantern":1,"minecraft:green_candle":1,"minecraft:stone":326,"minecraft:stripped_dark_oak_log":4,"minecraft:crafting_table":22,"minecraft:cornflower":10,"minecraft:short_grass":14,"minecraft:sculk_sensor":4,"minecraft:lectern":2,"minecraft:copper_ore":1,"minecraft:tall_grass":1,"minecraft:deepslate_gold_ore":7,"minecraft:lapis_ore":4,"minecraft:sculk":622,"supplementaries:urn":37,"minecraft:coarse_dirt":49,"spell_engine:spell_binding":6,"minecraft:spruce_log":1,"minecraft:bee_nest":1,"minecraft:coal_ore":81,"minecraft:zombie_head":1,"minecraft:flower_pot":2,"minecraft:gravel":32,"minecraft:cobweb":11,"minecraft:polished_andesite":25},"minecraft:used":{"minecraft:iron_shovel":28,"minecraft:spruce_slab":121,"minecraft:diamond_hoe":683,"minecraft:shield":51,"minecraft:iron_sword":200,"minecraft:iron_chestplate":1,"minecraft:mutton":1,"minecraft:tuff":16,"minecraft:spruce_boat":1,"minecraft:waxed_oxidized_copper":1,"minecraft:cyan_terracotta":2,"minecraft:lava_bucket":13,"minecraft:polished_andesite_stairs":10,"minecraft:bow":62,"minecraft:furnace":7,"archers:netherite_longbow":2,"minecraft:stone_pickaxe":86,"minecraft:oak_planks":33,"minecraft:wooden_pickaxe":7,"paladins:diamond_great_hammer":12,"paladins:diamond_claymore":1713,"spell_engine:spell_binding":5,"minecraft:blast_furnace":14,"waystones:waystone":1,"minecraft:bread":96,"minecraft:gravel":2,"minecraft:polished_andesite_slab":5,"minecraft:grindstone":1,"minecraft:andesite":36,"minecraft:smooth_stone_slab":29,"minecraft:coarse_dirt":2,"minecraft:enchanting_table":1,"minecraft:stone_sword":89,"minecraft:flint_and_steel":33,"minecraft:spruce_planks":3,"minecraft:stone_hoe":12,"minecraft:trial_key":4,"minecraft:torch":101,"minecraft:dirt":1,"minecraft:anvil":3,"minecraft:wooden_axe":6,"minecraft:bookshelf":17,"paladins:golden_claymore":5,"minecraft:iron_axe":114,"minecraft:cooked_beef":17,"minecraft:cobbled_deepslate":315,"minecraft:iron_leggings":1,"minecraft:cooked_mutton":36,"minecraft:water_bucket":63,"minecraft:polished_andesite":24,"minecraft:mossy_cobblestone":22,"minecraft:crafting_table":29,"minecraft:white_bed":7,"archers:diamond_spear":1,"archers:rapid_crossbow":1,"minecraft:diamond_pickaxe":1596,"runes:crafting_altar":3,"minecraft:iron_pickaxe":221,"minecraft:stone_axe":67,"minecraft:blue_carpet":3,"minecraft:cobblestone":323,"minecraft:cooked_porkchop":33,"minecraft:bucket":69,"minecraft:smooth_stone":2},"minecraft:dropped":{"minecraft:iron_sword":14,"minecraft:candle":6,"minecraft:moss_block":15,"minecraft:porkchop":5,"minecraft:lapis_lazuli":18,"minecraft:cooked_beef":23,"minecraft:glow_ink_sac":5,"minecraft:glass_bottle":4,"minecraft:diamond":69,"minecraft:crafting_table":1,"minecraft:cooked_porkchop":32,"minecraft:orange_tulip":3,"minecraft:lantern":3,"minecraft:leather":12,"minecraft:cobblestone_stairs":1,"minecraft:emerald":32,"minecraft:cyan_terracotta":3,"minecraft:dirt":32,"minecraft:mutton":14,"minecraft:gold_nugget":23,"minecraft:iron_pickaxe":2,"minecraft:white_wool":16,"minecraft:gold_ingot":2,"minecraft:bone":68,"minecraft:green_candle":3,"minecraft:gravel":14,"minecraft:white_tulip":1,"minecraft:stone_axe":1,"minecraft:sugar_cane":13,"minecraft:polished_andesite_slab":1,"minecraft:cobbled_deepslate":160,"minecraft:birch_sapling":1,"minecraft:pointed_dripstone":2,"minecraft:stripped_dark_oak_log":4,"minecraft:rotten_flesh":137,"minecraft:oak_planks":6,"minecraft:white_candle":4,"minecraft:glowstone_dust":2,"minecraft:cooked_mutton":30,"minecraft:white_bed":1,"supplementaries:antique_ink":5,"minecraft:poppy":3,"supplementaries:ash":45,"minecraft:gunpowder":9,"minecraft:skeleton_skull":3,"minecraft:ladder":1,"minecraft:azalea":4,"minecraft:brown_candle":2,"minecraft:spruce_slab":2,"minecraft:stone_brick_stairs":1,"minecraft:egg":4,"minecraft:enchanted_book":2,"minecraft:water_bucket":2,"minecraft:iron_ingot":23,"minecraft:wheat_seeds":2,"minecraft:mossy_cobblestone":25,"paladins:golden_claymore":1,"minecraft:iron_helmet":1,"minecraft:feather":3,"minecraft:cobblestone":113,"minecraft:apple":8,"minecraft:tropical_fish":2,"minecraft:grass_block":2,"minecraft:coal":19,"minecraft:polished_andesite":2,"minecraft:stick":34,"minecraft:oxeye_daisy":1,"minecraft:blue_dye":9,"minecraft:black_candle":1,"minecraft:diorite":1,"minecraft:wooden_axe":1,"minecraft:brown_wool":1,"minecraft:zombie_head":1,"minecraft:iron_leggings":3,"minecraft:oak_stairs":1,"minecraft:pumpkin":7,"minecraft:polished_andesite_stairs":5,"minecraft:iron_axe":1,"minecraft:mossy_cobblestone_stairs":4,"minecraft:smooth_stone":9,"paladins:diamond_claymore":2,"minecraft:iron_shovel":1,"minecraft:paper":6,"minecraft:string":5,"minecraft:spruce_sapling":2,"minecraft:bricks":2,"minecraft:moss_carpet":11,"minecraft:flow_pottery_sherd":1,"minecraft:coarse_dirt":66,"minecraft:stone_sword":1,"minecraft:raw_copper":3,"minecraft:smooth_stone_slab":2,"minecraft:tuff":9,"minecraft:chicken":2,"minecraft:light_gray_wool":3,"minecraft:clay_ball":136,"minecraft:iron_boots":2,"minecraft:damaged_anvil":1,"minecraft:name_tag":1,"minecraft:big_dripleaf":2,"minecraft:cobblestone_slab":1,"minecraft:potato":7,"minecraft:shield":1,"minecraft:spruce_planks":1,"minecraft:diamond_pickaxe":2,"minecraft:iron_chestplate":1,"minecraft:andesite":57,"minecraft:oak_sapling":1,"minecraft:spider_eye":5,"minecraft:spruce_log":1,"minecraft:bow":3,"minecraft:stone_pickaxe":2,"minecraft:wooden_pickaxe":1,"minecraft:red_tulip":6,"minecraft:black_wool":2},"minecraft:custom":{"minecraft:interact_with_crafting_table":84,"minecraft:open_barrel":20,"minecraft:eat_cake_slice":1,"minecraft:leave_game":9,"minecraft:time_since_death":219375,"minecraft:sprint_one_cm":1013903,"minecraft:damage_blocked_by_shield":4008,"minecraft:drop":334,"minecraft:talked_to_villager":9,"minecraft:play_time":423546,"minecraft:deaths":5,"minecraft:jump":6578,"minecraft:walk_on_water_one_cm":46140,"minecraft:enchant_item":8,"minecraft:interact_with_furnace":43,"minecraft:sleep_in_bed":4,"minecraft:waystone_activated":7,"minecraft:damage_dealt":127167,"minecraft:player_kills":2,"minecraft:crouch_one_cm":108068,"minecraft:inspect_dispenser":3,"minecraft:inspect_dropper":1,"minecraft:interact_with_anvil":2,"minecraft:mob_kills":699,"minecraft:climb_one_cm":17651,"minecraft:walk_one_cm":794136,"minecraft:sneak_time":32377,"minecraft:walk_under_water_one_cm":19511,"minecraft:boat_one_cm":105303,"minecraft:interact_with_blast_furnace":11,"minecraft:total_world_time":423546,"minecraft:interact_with_grindstone":5,"minecraft:time_since_rest":219407,"minecraft:damage_taken":10360,"minecraft:swim_one_cm":101684,"minecraft:fly_one_cm":1113388,"minecraft:open_chest":91,"minecraft:fall_one_cm":187257},"minecraft:killed_by":{"minecraft:creeper":1,"minecraft:zombie":2,"minecraft:player":1,"minecraft:iron_golem":1}},"DataVersion":3955}